odoo9_addon_sale_cancel_reason-9.0.1.0.0-py2.7-nspkg.pth
odoo9_addon_sale_cancel_reason-9.0.1.0.0.dist-info/DESCRIPTION.rst
odoo9_addon_sale_cancel_reason-9.0.1.0.0.dist-info/METADATA
odoo9_addon_sale_cancel_reason-9.0.1.0.0.dist-info/RECORD
odoo9_addon_sale_cancel_reason-9.0.1.0.0.dist-info/WHEEL
odoo9_addon_sale_cancel_reason-9.0.1.0.0.dist-info/metadata.json
odoo9_addon_sale_cancel_reason-9.0.1.0.0.dist-info/namespace_packages.txt
odoo9_addon_sale_cancel_reason-9.0.1.0.0.dist-info/top_level.txt
odoo_addons/sale_cancel_reason/README.rst
odoo_addons/sale_cancel_reason/__init__.py
odoo_addons/sale_cancel_reason/__openerp__.py
odoo_addons/sale_cancel_reason/data/sale_order_cancel_reason.xml
odoo_addons/sale_cancel_reason/i18n/de.po
odoo_addons/sale_cancel_reason/i18n/es.po
odoo_addons/sale_cancel_reason/i18n/fi.po
odoo_addons/sale_cancel_reason/i18n/fr.po
odoo_addons/sale_cancel_reason/i18n/it.po
odoo_addons/sale_cancel_reason/i18n/sale_cancel_reason.pot
odoo_addons/sale_cancel_reason/i18n/sl.po
odoo_addons/sale_cancel_reason/i18n/zh_CN.po
odoo_addons/sale_cancel_reason/models/__init__.py
odoo_addons/sale_cancel_reason/models/sale.py
odoo_addons/sale_cancel_reason/security/ir.model.access.csv
odoo_addons/sale_cancel_reason/static/description/1configuration.png
odoo_addons/sale_cancel_reason/static/description/2sale_order.png
odoo_addons/sale_cancel_reason/static/description/3reason.png
odoo_addons/sale_cancel_reason/static/description/4cancel_reason_so.png
odoo_addons/sale_cancel_reason/static/description/icon.png
odoo_addons/sale_cancel_reason/tests/__init__.py
odoo_addons/sale_cancel_reason/tests/test_sale.py
odoo_addons/sale_cancel_reason/views/sale_view.xml
odoo_addons/sale_cancel_reason/wizard/__init__.py
odoo_addons/sale_cancel_reason/wizard/cancel_reason.py
odoo_addons/sale_cancel_reason/wizard/cancel_reason_view.xml
